bettermonitoring/__init__.py
bettermonitoring/core.py
bettermonitoring/models.py
bettermonitoring-0.1.3.dist-info/LICENSE
bettermonitoring-0.1.3.dist-info/WHEEL
bettermonitoring-0.1.3.dist-info/METADATA
bettermonitoring-0.1.3.dist-info/RECORD
