Metadata-Version: 2.1
Name: bettermonitoring
Version: 0.1.3
Summary: 
Author: Roman
Requires-Python: >=3.10,<4.0
Classifier: Programming Language :: Python :: 3
Classifier: Programming Language :: Python :: 3.10
Requires-Dist: httpx (>=0.22.0,<0.23.0)
